browsercam/__init__.py
browsercam/webcam.html
browsercam-0.2.dist-info/METADATA
browsercam-0.2.dist-info/WHEEL
browsercam-0.2.dist-info/top_level.txt
browsercam-0.2.dist-info/RECORD
